json_log_utils/__init__.py
json_log_utils/logger.py
json_log_utils-0.2.dist-info/METADATA
json_log_utils-0.2.dist-info/WHEEL
json_log_utils-0.2.dist-info/top_level.txt
json_log_utils-0.2.dist-info/RECORD
